<?xml version='1.0' encoding='UTF-8' standalone='yes' ?><hierarchy rotation="0"><node index="0" text="" resource-id="" class="android.widget.FrameLayout" package="com.flights.studio" content-desc="" checkable="false" checked="false" clickable="false" enabled="true" focusable="false" focused="false" scrollable="false" long-clickable="false" password="false" selected="false" bounds="[0,0][1440,3120]" drawing-order="0" hint=""><node index="0" text="" resource-id="" class="android.widget.FrameLayout" package="com.flights.studio" content-desc="" checkable="false" checked="false" clickable="false" enabled="true" focusable="false" focused="false" scrollable="false" long-clickable="false" password="false" selected="false" bounds="[0,0][1440,3120]" drawing-order="2" hint="" /><node index="1" text="" resource-id="" class="android.widget.LinearLayout" package="com.flights.studio" content-desc="" checkable="false" checked="false" clickable="false" enabled="true" focusable="false" focused="false" scrollable="false" long-clickable="false" password="false" selected="false" bounds="[0,0][1440,3120]" drawing-order="1" hint=""><node index="0" text="" resource-id="android:id/content" class="android.widget.FrameLayout" package="com.flights.studio" content-desc="" checkable="false" checked="false" clickable="false" enabled="true" focusable="false" focused="false" scrollable="false" long-clickable="false" password="false" selected="false" bounds="[0,0][1440,3120]" drawing-order="2" hint=""><node index="0" text="" resource-id="" class="android.widget.FrameLayout" package="com.flights.studio" content-desc="" checkable="false" checked="false" clickable="false" enabled="true" focusable="false" focused="false" scrollable="false" long-clickable="false" password="false" selected="false" bounds="[0,0][1440,3120]" drawing-order="1" hint=""><node index="0" text="" resource-id="" class="android.view.View" package="com.flights.studio" content-desc="" checkable="false" checked="false" clickable="false" enabled="true" focusable="false" focused="false" scrollable="false" long-clickable="false" password="false" selected="false" bounds="[0,0][1440,3120]" drawing-order="3" hint="" /><node index="1" text="" resource-id="" class="android.widget.FrameLayout" package="com.flights.studio" content-desc="" checkable="false" checked="false" clickable="false" enabled="true" focusable="true" focused="false" scrollable="false" long-clickable="false" password="false" selected="false" bounds="[0,0][1440,3120]" drawing-order="1" hint=""><node index="0" text="" resource-id="" class="android.widget.FrameLayout" package="com.flights.studio" content-desc="" checkable="false" checked="false" clickable="false" enabled="true" focusable="false" focused="false" scrollable="false" long-clickable="false" password="false" selected="false" bounds="[0,0][1440,3120]" drawing-order="1" hint=""><node index="0" text="" resource-id="" class="android.widget.FrameLayout" package="com.flights.studio" content-desc="" checkable="false" checked="false" clickable="false" enabled="true" focusable="false" focused="false" scrollable="false" long-clickable="false" password="false" selected="false" bounds="[0,0][1440,3067]" drawing-order="2" hint="" /><node index="1" text="" resource-id="" class="android.widget.FrameLayout" package="com.flights.studio" content-desc="" checkable="false" checked="false" clickable="false" enabled="true" focusable="false" focused="false" scrollable="false" long-clickable="false" password="false" selected="false" bounds="[0,0][1440,3067]" drawing-order="4" hint=""><node index="0" text="" resource-id="" class="android.widget.FrameLayout" package="com.flights.studio" content-desc="" checkable="false" checked="false" clickable="false" enabled="true" focusable="false" focused="false" scrollable="false" long-clickable="false" password="false" selected="false" bounds="[0,0][1440,3067]" drawing-order="1" hint="" /></node><node index="2" text="" resource-id="" class="android.widget.FrameLayout" package="com.flights.studio" content-desc="" checkable="false" checked="false" clickable="false" enabled="true" focusable="false" focused="false" scrollable="false" long-clickable="false" password="false" selected="false" bounds="[0,0][1440,3067]" drawing-order="3" hint=""><node index="0" text="" resource-id="" class="android.widget.ScrollView" package="com.flights.studio" content-desc="" checkable="false" checked="false" clickable="false" enabled="true" focusable="true" focused="false" scrollable="false" long-clickable="false" password="false" selected="false" bounds="[0,0][1440,3067]" drawing-order="1" hint=""><node index="0" text="" resource-id="" class="android.widget.FrameLayout" package="com.flights.studio" content-desc="" checkable="false" checked="false" clickable="false" enabled="true" focusable="false" focused="false" scrollable="false" long-clickable="false" password="false" selected="false" bounds="[0,0][1440,3067]" drawing-order="1" hint=""><node index="0" text="" resource-id="" class="androidx.viewpager.widget.ViewPager" package="com.flights.studio" content-desc="" checkable="false" checked="false" clickable="false" enabled="true" focusable="true" focused="false" scrollable="true" long-clickable="false" password="false" selected="false" bounds="[0,0][1440,3067]" drawing-order="2" hint=""><node index="1" text="" resource-id="" class="android.widget.FrameLayout" package="com.flights.studio" content-desc="" checkable="false" checked="false" clickable="false" enabled="true" focusable="false" focused="false" scrollable="false" long-clickable="false" password="false" selected="false" bounds="[0,0][1440,3067]" drawing-order="2" hint=""><node index="0" text="Free" resource-id="" class="android.widget.TextView" package="com.flights.studio" content-desc="" checkable="false" checked="false" clickable="false" enabled="true" focusable="false" focused="false" scrollable="false" long-clickable="false" password="false" selected="false" bounds="[63,1280][1377,1402]" drawing-order="1" hint="" /><node index="1" text="Relay X keeps chats and media available across your devices." resource-id="" class="android.widget.TextView" package="com.flights.studio" content-desc="" checkable="false" checked="false" clickable="false" enabled="true" focusable="false" focused="false" scrollable="false" long-clickable="false" password="false" selected="false" bounds="[56,1434][1384,1575]" drawing-order="2" hint="" /></node></node><node index="1" text="" resource-id="" class="android.widget.FrameLayout" package="com.flights.studio" content-desc="" checkable="false" checked="false" clickable="true" enabled="true" focusable="true" focused="false" scrollable="false" long-clickable="false" password="false" selected="false" bounds="[1202,154][1426,378]" drawing-order="6" hint=""><node index="0" text="" resource-id="" class="android.widget.ImageView" package="com.flights.studio" content-desc="Switch to night theme" checkable="false" checked="false" clickable="false" enabled="true" focusable="false" focused="false" scrollable="false" long-clickable="false" password="false" selected="false" bounds="[1265,217][1363,315]" drawing-order="1" hint="" /></node><node index="2" text="" resource-id="" class="android.widget.FrameLayout" package="com.flights.studio" content-desc="" checkable="false" checked="false" clickable="false" enabled="true" focusable="false" focused="false" scrollable="false" long-clickable="false" password="false" selected="false" bounds="[0,667][1440,1192]" drawing-order="1" hint=""><node index="0" text="" resource-id="" class="android.view.TextureView" package="com.flights.studio" content-desc="" checkable="false" checked="false" clickable="false" enabled="true" focusable="false" focused="false" scrollable="false" long-clickable="false" password="false" selected="false" bounds="[370,667][1070,1192]" drawing-order="1" hint="" /></node><node index="3" text="" resource-id="" class="android.view.View" package="com.flights.studio" content-desc="" checkable="false" checked="false" clickable="false" enabled="true" focusable="false" focused="false" scrollable="false" long-clickable="false" password="false" selected="false" bounds="[604,1679][835,1697]" drawing-order="4" hint="" /><node index="5" text="Start Messaging" resource-id="" class="android.widget.TextView" package="com.flights.studio" content-desc="" checkable="false" checked="false" clickable="true" enabled="true" focusable="true" focused="false" scrollable="false" long-clickable="false" password="false" selected="false" bounds="[160,2597][1280,2765]" drawing-order="3" hint="" /></node></node></node><node index="3" text="" resource-id="" class="android.widget.FrameLayout" package="com.flights.studio" content-desc="Web tabs " checkable="false" checked="false" clickable="false" enabled="true" focusable="false" focused="false" scrollable="false" long-clickable="false" password="false" selected="false" bounds="[0,2801][1440,3067]" drawing-order="1" hint="" /></node></node></node></node></node></node></hierarchy>